ptunnel/__init__.py
ptunnel/__main__.py
ptunnel/client/__init__.py
ptunnel/server/__init__.py
ptunnel/server/config.py
ptunnel/server/serve.py
sparcs_ptunnel-1.1.0.dist-info/LICENSE
sparcs_ptunnel-1.1.0.dist-info/METADATA
sparcs_ptunnel-1.1.0.dist-info/WHEEL
sparcs_ptunnel-1.1.0.dist-info/entry_points.txt
sparcs_ptunnel-1.1.0.dist-info/top_level.txt
sparcs_ptunnel-1.1.0.dist-info/RECORD
