Metadata-Version: 2.1
Name: sparcs-ptunnel
Version: 1.1.0
Summary: Simple port forwarding tool for SPARCS
Author: Roul
Author-email: roul@sparcs.org
Classifier: Programming Language :: Python :: 3
Classifier: License :: OSI Approved :: GNU General Public License v3 (GPLv3)
Classifier: Operating System :: OS Independent
Requires-Python: >=3.8.0
License-File: LICENSE
Requires-Dist: prompt-toolkit
Requires-Dist: pycryptodome
Requires-Dist: click
Requires-Dist: flask
Requires-Dist: flask-cors
Requires-Dist: requests
